{
  "users": [
    {
      "usermail": "m@gmail.com",
      "password": "123456",
      "gender": "men",
      "cart": [],
      "mydesigners": [],
      "id": "1"
    },
    {
      "usermail": "g@gmail.com",
      "password": "999000",
      "cart": [],
      "mydesigners": [],
      "id": "2"
    },
    {
      "usermail": "z@gmail.com",
      "password": "1111",
      "cart": [],
      "mydesigners": [],
      "isloggedin": false,
      "id": "3"
    },
    {
      "usermail": "mmm@gmail.com",
      "password": "9980",
      "cart": [
        {
          "id": 50,
          "designer": "ACNE STUDIOS",
          "title": "Midsummer Shopper Bag",
          "price": 57119.75,
          "image": "https://is4.fwrdassets.com/images/p/fw/45/ACNE-WY93_V1.jpg",
          "new": "false",
          "category": "bags"
        },
        {
          "id": 46,
          "designer": "ADIDAS ORIGINALS",
          "title": "Rivalry 86 Low Sneaker",
          "price": 10006.38,
          "image": "https://is4.fwrdassets.com/images/p/fw/z/ADIO-MZ224_V1.jpg",
          "new": "true",
          "category": "shoes"
        }
      ],
      "mydesigners": [],
      "isloggedin": true,
      "wishlist": [
        {
          "id": 50,
          "designer": "ACNE STUDIOS",
          "title": "Midsummer Shopper Bag",
          "price": 57119.75,
          "image": "https://is4.fwrdassets.com/images/p/fw/45/ACNE-WY93_V1.jpg",
          "new": "false",
          "category": "bags"
        },
        {
          "id": 46,
          "designer": "ADIDAS ORIGINALS",
          "title": "Rivalry 86 Low Sneaker",
          "price": 10006.38,
          "image": "https://is4.fwrdassets.com/images/p/fw/z/ADIO-MZ224_V1.jpg",
          "new": "true",
          "category": "shoes"
        }
      ],
      "id": "4"
    },
    {
      "usermail": "ss@gmail.com",
      "password": "1234",
      "cart": [
        {
          "id": 42,
          "designer": "AGOLDE",
          "title": "Harper Mid Rise Straight",
          "price": 18178,
          "image": "https://is4.fwrdassets.com/images/p/fw/z/AGOL-WJ530_V1.jpg",
          "new": "true",
          "category": "dress",
          "quantity": 1
        }
      ],
      "mydesigners": [
        "BAINA",
        "A.L.C.",
        "BALENCIAGA",
        "A'MMONDE ATELIER",
        "CAMP HIGH",
        "HELSA",
        "ALBERTA FERRETTI",
        "ANASTASIO HOME",
        "BHANDON",
        "BIRKENSTOCK",
        "BOYY",
        "BIBA DE SOUSA",
        "BRANDON MAXWELL",
        "ETRO",
        "BIANCA",
        "ANDREADAMO",
        "ACNE STUDIOS",
        "BALLY",
        "DAVID KOMA",
        "ETERNE",
        "ERL",
        "CALLE DEL MAR",
        "MACH & MACH",
        "U BEAUTY",
        "ULLA JOHNSON",
        "UNIFROM",
        "CANADA GOOSE",
        "DIOTIMA",
        "FLATLIST",
        "ISABEL MARANT",
        "FOREO",
        "WOLFORD",
        "OLIVE ATELIERS",
        "A.EMERY",
        "ALANUI",
        "CHRISTOPHER ESBER",
        "COPERNI",
        "DIESEL",
        "FREDERIC MALLE",
        "EERA",
        "GANNI"
      ],
      "isloggedin": true,
      "wishlist": [
        {
          "id": 3,
          "image": "https://is4.fwrdassets.com/images/p/fw/p/SPOF-WD363_V1.jpg",
          "designer": "self-portrait",
          "title": "Crepe Bow Mini Dress",
          "price": 38651,
          "category": "clothing"
        },
        {
          "id": 133,
          "designer": "ANASTASIO HOME",
          "title": "Swell Candle Set",
          "price": 16260,
          "image": "https://is4.fwrdassets.com/images/p/fw/45/AOMF-WH42_V3.jpg",
          "new": "true",
          "category": "beauty"
        }
      ],
      "id": "5"
    },
    {
      "id": "1844",
      "usermail": "rebel@gmail.com",
      "password": "12345",
      "cart": [
        {
          "id": "1",
          "image": "https://is4.fwrdassets.com/images/p/fw/p/NOMF-WD478_V1.jpg",
          "designer": "Norma Kamali",
          "title": "Strapless Bill Pickleball Dress",
          "price": 32833,
          "category": "clothing"
        },
        {
          "id": "1",
          "image": "https://is4.fwrdassets.com/images/p/fw/p/NOMF-WD478_V1.jpg",
          "designer": "Norma Kamali",
          "title": "Strapless Bill Pickleball Dress",
          "price": 32833,
          "category": "clothing"
        }
      ],
      "mydesigners": [
        "A'MMONDE ATELIER"
      ],
      "isloggedin": true,
      "wishlist": [
        {
          "id": "2",
          "image": "https://is4.fwrdassets.com/images/p/fw/p/RTFF-WP31_V1.jpg",
          "designer": "retrofete",
          "title": "Danica Pant",
          "price": 24520,
          "category": "clothing"
        }
      ]
    },
    {
      "id": "ddc5",
      "usermail": "rohit@gmail.com",
      "password": "12345",
      "cart": [],
      "mydesigners": [],
      "isloggedin": false,
      "wishlist": []
    },
    {
      "id": "e03f",
      "usermail": "wdfcef",
      "password": "12345",
      "cart": [],
      "mydesigners": [],
      "isloggedin": false,
      "wishlist": []
    },
    {
      "id": "a3f4",
      "usermail": "",
      "password": "123",
      "cart": [],
      "mydesigners": [],
      "isloggedin": false,
      "wishlist": []
    },
    {
      "usermail": "rakeshrodda@gmail.com",
      "password": "1234",
      "cart": [],
      "mydesigners": [],
      "isloggedin": false,
      "wishlist": [],
      "id": "xd5GZVX"
    }
  ],
  "data": [
    {
      "id": "1",
      "image": "https://is4.fwrdassets.com/images/p/fw/p/NOMF-WD478_V1.jpg",
      "designer": "Norma Kamali",
      "title": "Strapless Bill Pickleball Dress",
      "price": 32833,
      "category": "clothing"
    },
    {
      "id": "2",
      "image": "https://is4.fwrdassets.com/images/p/fw/p/RTFF-WP31_V1.jpg",
      "designer": "retrofete",
      "title": "Danica Pant",
      "price": 24520,
      "category": "clothing"
    },
    {
      "id": "3",
      "image": "https://is4.fwrdassets.com/images/p/fw/p/SPOF-WD363_V1.jpg",
      "designer": "self-portrait",
      "title": "Crepe Bow Mini Dress",
      "price": 38651,
      "category": "clothing"
    },
    {
      "id": "4",
      "image": "https://is4.fwrdassets.com/images/p/fw/p/NOMF-WC108_V1.jpg",
      "designer": "Norma Kamali",
      "title": "Long Sleeve Turtleneck Catsuit with Footie",
      "price": 13299,
      "category": "clothing"
    },
    {
      "id": "5",
      "image": "https://is4.fwrdassets.com/images/p/fw/p/HLSA-WO9_V1.jpg",
      "designer": "Helsa",
      "title": "Tech Gabardine Zip Jacket",
      "price": 27263,
      "category": "clothing"
    },
    {
      "id": "6",
      "image": "https://is4.fwrdassets.com/images/p/fw/p/CHRF-WD212_V1.jpg",
      "designer": "Christopher Esber",
      "title": "Molded Venus Dress",
      "price": 80544,
      "category": "clothing"
    },
    {
      "id": "7",
      "image": "https://is4.fwrdassets.com/images/p/fw/p/NOMF-WD342_V1.jpg",
      "designer": "Norma Kamali",
      "title": "Long Sleeve Turtleneck Fishtail Mini Dress",
      "price": 17871,
      "category": "clothing"
    },
    {
      "id": "8",
      "image": "https://is4.fwrdassets.com/images/p/fw/p/HLSA-WD39_V1.jpg",
      "designer": "Helsa",
      "title": "Matte Jersey Off Shoulder Maxi Dress",
      "price": 18951,
      "category": "clothing"
    },
    {
      "id": "9",
      "image": "https://is4.fwrdassets.com/images/p/fw/p/NOMF-WD468_V1.jpg",
      "designer": "Norma Kamali",
      "title": "Long Sleeve Turtleneck Pickleball Dress",
      "price": 18702,
      "category": "clothing"
    },
    {
      "id": "10",
      "image": "https://is4.fwrdassets.com/images/p/fw/p/ENZF-WP57_V1.jpg",
      "designer": "Enza Costa",
      "title": "Twill Everywhere Pant",
      "price": 24520,
      "category": "clothing"
    },
    {
      "id": "11",
      "image": "https://is4.fwrdassets.com/images/p/fw/p/BLMF-WD131_V1.jpg",
      "designer": "BALMAIN",
      "title": "Long Sleeve Buttoned Short Dress",
      "price": 273470,
      "category": "clothing"
    },
    {
      "id": "12",
      "image": "https://is4.fwrdassets.com/images/p/fw/p/NOMF-WD463_V1.jpg",
      "designer": "Norma Kamali",
      "title": "One Sleeve Drop Shoulder Side Drape Mini Dress",
      "price": 16208,
      "category": "clothing"
    },
    {
      "id": "13",
      "image": "https://is4.fwrdassets.com/images/p/fw/p/RTFF-WD319_V1.jpg",
      "designer": "retrofete",
      "title": "Nicole Dress",
      "price": 49457,
      "category": "clothing"
    },
    {
      "id": "14",
      "image": "https://is4.fwrdassets.com/images/p/fw/p/NOMF-WS78_V1.jpg",
      "designer": "Norma Kamali",
      "title": "Oversized Boyfriend Shirt Bodysuit",
      "price": 17871,
      "category": "clothing"
    },
    {
      "id": "15",
      "image": "https://is4.fwrdassets.com/images/p/fw/p/JQUF-WD132_V1.jpg",
      "designer": "JACQUEMUS",
      "title": "La Robe Bari",
      "price": 91433,
      "category": "clothing"
    },
    {
      "id": "16",
      "image": "https://is4.fwrdassets.com/images/p/fw/p/NOMF-WD375_V1.jpg",
      "designer": "Norma Kamali",
      "title": "Oversized Shirt Shirred Bottom Mini Dress",
      "price": 15377,
      "category": "clothing"
    },
    {
      "id": "17",
      "image": "https://is4.fwrdassets.com/images/p/fw/p/NOMF-WC121_V1.jpg",
      "designer": "Norma Kamali",
      "title": "Long Sleeve Deep V Neck Catsuit",
      "price": 16208,
      "category": "clothing"
    },
    {
      "id": "18",
      "image": "https://is4.fwrdassets.com/images/p/fw/p/MAYF-WD8_V1.jpg",
      "designer": "Maygel Coronel",
      "title": "Veranera Dress",
      "price": 42392,
      "category": "clothing"
    },
    {
      "id": "19",
      "image": "https://is4.fwrdassets.com/images/p/fw/p/NOMF-WD451_V1.jpg",
      "designer": "Norma Kamali",
      "title": "Sleeveless Pickleball Mini Dress",
      "price": 12052,
      "category": "clothing"
    },
    {
      "id": "20",
      "image": "https://is4.fwrdassets.com/images/p/fw/p/NOMF-WD465_V1.jpg",
      "designer": "Norma Kamali",
      "title": "Spliced Fishtail Gown",
      "price": 21196,
      "category": "clothing"
    },
    {
      "id": "21",
      "image": "https://is4.fwrdassets.com/images/p/fw/p/NOMF-WD378_V1.jpg",
      "designer": "Norma Kamali",
      "title": "Sleeveless Pickleball Mini Dress",
      "price": 12052,
      "category": "clothing"
    },
    {
      "id": "22",
      "image": "https://is4.fwrdassets.com/images/p/fw/p/NOMF-WD323_V1.jpg",
      "designer": "Norma Kamali",
      "title": "Turtleneck Strapless Fishtail Gown",
      "price": 22858,
      "category": "clothing"
    },
    {
      "id": "23",
      "image": "https://is4.fwrdassets.com/images/p/fw/p/GRLR-WJ604_V1.jpg",
      "designer": "GRLFRND",
      "title": "Camille High Rise Flared Trouser",
      "price": 20364,
      "category": "clothing"
    },
    {
      "id": "24",
      "image": "https://is4.fwrdassets.com/images/p/fw/p/SMEF-WD9_V1.jpg",
      "designer": "Shani Shemer",
      "title": "Lily Maxi Dress",
      "price": 41145,
      "category": "clothing"
    },
    {
      "id": "25",
      "image": "https://is4.fwrdassets.com/images/p/fw/p/ENZF-WD476_V1.jpg",
      "designer": "Enza Costa",
      "title": "Knit Turtleneck Mini Tunic Dress",
      "price": 18702,
      "category": "clothing"
    },
    {
      "id": "26",
      "image": "https://is4.fwrdassets.com/images/p/fw/p/JSIM-WD558_V1.jpg",
      "designer": "SIMKHAI",
      "title": "Arta Bustier Mini Dress",
      "price": 61925,
      "category": "clothing"
    },
    {
      "id": "27",
      "image": "https://is4.fwrdassets.com/images/p/fw/p/CITI-WJ1803_V1.jpg",
      "designer": "Citizens of Humanity",
      "title": "Ayla Baggy Cuffed Crop",
      "price": 22276,
      "category": "clothing"
    },
    {
      "id": "28",
      "image": "https://is4.fwrdassets.com/images/p/fw/p/NOMF-WD310_V1.jpg",
      "designer": "Norma Kamali",
      "title": "One Shoulder Bias Gown",
      "price": 27014,
      "category": "clothing"
    },
    {
      "id": "29",
      "image": "https://is4.fwrdassets.com/images/p/fw/p/AGOL-WJ446_V1.jpg",
      "designer": "AGOLDE",
      "title": "90's Pinch Waist",
      "price": 16458,
      "category": "clothing"
    },
    {
      "id": "30",
      "image": "https://is4.fwrdassets.com/images/p/fw/p/RTFF-WD442_V1.jpg",
      "designer": "retrofete",
      "title": "Ember Dress",
      "price": 57769,
      "category": "clothing"
    },
    {
      "id": "31",
      "image": "https://is4.fwrdassets.com/images/p/fw/p/NOMF-WD447_V1.jpg",
      "designer": "Norma Kamali",
      "title": "Super Oversized Boyfriend Shirt Flared Gown",
      "price": 20364,
      "category": "clothing"
    },
    {
      "id": "32",
      "image": "https://is4.fwrdassets.com/images/p/fw/p/RTFF-WD299_V1.jpg",
      "designer": "retrofete",
      "title": "Candice Gown",
      "price": 61925,
      "category": "clothing"
    },
    {
      "id": "33",
      "image": "https://is4.fwrdassets.com/images/p/fw/p/NOMF-WD314_V1.jpg",
      "designer": "Norma Kamali",
      "title": "Long Sleeve Turtleneck Side Drape Gown",
      "price": 12168,
      "category": "clothing"
    },
    {
      "id": "34",
      "image": "https://is4.fwrdassets.com/images/p/fw/p/NOMF-WD485_V1.jpg",
      "designer": "Norma Kamali",
      "title": "Long Sleeve Turtleneck Side Drape Gown",
      "price": 12468,
      "category": "clothing"
    },
    {
      "id": "35",
      "image": "https://is4.fwrdassets.com/images/p/fw/p/SEDF-WD28_V1.jpg",
      "designer": "SIEDRES",
      "title": "Nisha Sun Ray Printed Dress",
      "price": 29757,
      "category": "clothing"
    },
    {
      "id": "36",
      "image": "https://is4.fwrdassets.com/images/p/fw/p/PTAB-WD256_V1.jpg",
      "designer": "PatBO",
      "title": "Twist Top Fringe Midi Dress",
      "price": 62341,
      "category": "clothing"
    },
    {
      "id": "37",
      "image": "https://is4.fwrdassets.com/images/p/fw/p/NOMF-WD374_V1.jpg",
      "designer": "Norma Kamali",
      "title": "Long Sleeve Diana Gown",
      "price": 18702,
      "category": "clothing"
    },
    {
      "id": "38",
      "image": "https://is4.fwrdassets.com/images/p/fw/p/RTFF-WD342_V1.jpg",
      "designer": "retrofete",
      "title": "Regina Dress",
      "price": 49457,
      "category": "clothing"
    },
    {
      "id": "39",
      "image": "https://is4.fwrdassets.com/images/p/fw/p/NOMF-WP68_V1.jpg",
      "designer": "Norma Kamali",
      "title": "Thigh High Spliced Legging",
      "price": 8229,
      "category": "clothing"
    },
    {
      "id": "40",
      "designer": "ACNE STUDIOS",
      "title": "Varong Sarong",
      "price": 39191,
      "image": "https://is4.fwrdassets.com/images/p/fw/z/ACNE-WA211_V1.jpg",
      "new": "true",
      "category": "dress"
    },
    {
      "id": "41",
      "designer": "ACNE STUDIOS",
      "title": "Holtz Lace Camo Sun Hat",
      "price": 35022,
      "image": "https://is4.fwrdassets.com/images/p/fw/45s/ACNE-WA212_V1.jpg",
      "new": "true",
      "category": "dress"
    },
    {
      "id": "42",
      "designer": "AGOLDE",
      "title": "Harper Mid Rise Straight",
      "price": 18178,
      "image": "https://is4.fwrdassets.com/images/p/fw/z/AGOL-WJ530_V1.jpg",
      "new": "true",
      "category": "dress"
    },
    {
      "id": "43",
      "designer": "AJE",
      "title": "Cordelia Corsetted Maxi Dress",
      "price": 52116,
      "image": "https://is4.fwrdassets.com/images/p/fw/z/AJEF-WD92_V1.jpg",
      "new": "true",
      "category": "dress"
    },
    {
      "id": "44",
      "designer": "BODE",
      "title": "Ace Of Spades Dress",
      "price": 57536,
      "image": "https://is4.fwrdassets.com/images/p/fw/z/BOFE-WD12_V1.jpg",
      "new": "true",
      "category": "dress"
    },
    {
      "id": "45",
      "designer": "ALC",
      "title": "Delfina Dress",
      "price": 57953,
      "image": "https://is4.fwrdassets.com/images/p/fw/z/ALC-WD524_V1.jpg",
      "new": "false",
      "category": "clothing"
    },
    {
      "id": "46",
      "designer": "ADIDAS ORIGINALS",
      "title": "Rivalry 86 Low Sneaker",
      "price": 10006,
      "image": "https://is4.fwrdassets.com/images/p/fw/z/ADIO-MZ224_V1.jpg",
      "new": "true",
      "category": "shoes"
    },
    {
      "id": "47",
      "designer": "ALPHA INDUSTRIES",
      "title": "Panel Jacket",
      "price": 10339,
      "image": "https://is4.fwrdassets.com/images/p/fw/z/ALPF-MO100_V1.jpg",
      "new": "false",
      "category": "clothing"
    },
    {
      "id": "48",
      "designer": "AMBUSH",
      "title": "Graphic Crewneck",
      "price": 57119,
      "image": "https://is4.fwrdassets.com/images/p/fw/z/ASBM-MK8_V1.jpg",
      "new": "false",
      "category": "clothing"
    },
    {
      "id": "49",
      "designer": "AMBUSH",
      "title": "Graphic Crewneck",
      "price": 57119,
      "image": "https://is4.fwrdassets.com/images/p/fw/z/FNEF-WZ2_V1.jpg",
      "new": "false",
      "category": "shoes"
    },
    {
      "id": "50",
      "designer": "ACNE STUDIOS",
      "title": "Midsummer Shopper Bag",
      "price": 57119,
      "image": "https://is4.fwrdassets.com/images/p/fw/45/ACNE-WY93_V1.jpg",
      "new": "false",
      "category": "bags"
    },
    {
      "id": "51",
      "designer": "BALENCIAGA",
      "title": "BB Soft Flap Small Bag",
      "price": 57119,
      "image": "https://is4.fwrdassets.com/images/p/fw/45/BALF-WY1457_V1.jpg",
      "new": "false",
      "category": "bags"
    },
    {
      "id": "52",
      "designer": "JANESSA LEONE",
      "title": "Beca Backpack",
      "price": 57119,
      "image": "https://is4.fwrdassets.com/images/p/fw/45/JLEO-WY2_V1.jpg",
      "new": "false",
      "category": "bags"
    },
    {
      "id": "53",
      "designer": "FWRD RENEW",
      "title": "Saint Laurent Small Kate Chain Bag",
      "price": 57119,
      "image": "https://is4.fwrdassets.com/images/p/fw/45/FNEF-WY2925_V1.jpg",
      "new": "false",
      "category": "bags"
    },
    {
      "id": "54",
      "designer": "FWRD RENEW",
      "title": "Saint Laurent Small Kate Chain Bag",
      "price": 57119,
      "image": "https://is4.fwrdassets.com/images/p/fw/45/FNEF-WY2932_V1.jpg",
      "new": "false",
      "category": "bags"
    },
    {
      "id": "55",
      "designer": "FWRD RENEW",
      "title": "Bottega Veneta The Pouch Chain Bag",
      "price": 57119,
      "image": "https://is4.fwrdassets.com/images/p/fw/45/FNEF-WY16_V1.jpg",
      "new": "false",
      "category": "bags"
    },
    {
      "id": "56",
      "designer": "BOTTEGA VENETA",
      "title": "Micro Arco Tote Bag",
      "price": 57119,
      "image": "https://is4.fwrdassets.com/images/p/fw/45/BOTT-WY1675_V1.jpg",
      "new": "false",
      "category": "bags"
    },
    {
      "id": "57",
      "designer": "FWRD RENEW",
      "title": "Gucci GG Marmont Waist Bag",
      "price": 57119,
      "image": "https://is4.fwrdassets.com/images/p/fw/45/FNEF-WY2913_V1.jpg",
      "new": "false",
      "category": "bags"
    },
    {
      "id": "58",
      "designer": "BOTTEGA VENETA",
      "title": "Mini Jodie Bag",
      "price": 57119,
      "image": "https://is4.fwrdassets.com/images/p/fw/45/BOTT-WY1676_V1.jpg",
      "new": "false",
      "category": "bags"
    },
    {
      "id": "59",
      "designer": "FWRD RENEW",
      "title": "Channel Boy Wallet On Chain Bag",
      "price": 57119,
      "image": "https://is4.fwrdassets.com/images/p/fw/45/FNEF-WY3159_V1.jpg",
      "new": "false",
      "category": "bags"
    },
    {
      "id": "60",
      "designer": "FWRD RENEW",
      "title": "The Row Small North South Park Tote Bag",
      "price": 57119,
      "image": "https://is4.fwrdassets.com/images/p/fw/45/FNEF-WY3006_V1.jpg",
      "new": "false",
      "category": "bags"
    },
    {
      "id": "61",
      "designer": "FWRD RENEW",
      "title": "Fendi Bucket Embroidered 2 Way Shoulder Bag",
      "price": 57119,
      "image": "https://is4.fwrdassets.com/images/p/fw/45/FNEF-WY3209_V1.jpg",
      "new": "false",
      "category": "bags"
    },
    {
      "id": "62",
      "designer": "BOTTEGA VENETA",
      "title": "Small Hop Bag",
      "price": 57119,
      "image": "https://is4.fwrdassets.com/images/p/fw/45/BOTT-WY1673_V1.jpg",
      "new": "false",
      "category": "bags"
    },
    {
      "id": "63",
      "designer": "BOTTEGA VENETA",
      "title": "Tag Holder",
      "price": 57119,
      "image": "https://is4.fwrdassets.com/images/p/fw/45/BOTT-WA287_V1.jpg",
      "new": "false",
      "category": "accessories"
    },
    {
      "id": "64",
      "designer": "CULT GAIA",
      "title": "Brynn Tote Bag",
      "price": 57119,
      "image": "https://is4.fwrdassets.com/images/p/fw/45/GAIA-WY134_V1.jpg",
      "new": "false",
      "category": "bags"
    },
    {
      "id": "65",
      "designer": "BODE",
      "title": "Clothesline Tote Bag",
      "price": 57119,
      "image": "https://is4.fwrdassets.com/images/p/fw/45/BOFE-WY2_V1.jpg",
      "new": "false",
      "category": "bags"
    },
    {
      "id": "66",
      "designer": "PARAVEL",
      "title": "Packing Cube Quad Case",
      "price": 57119,
      "image": "https://is4.fwrdassets.com/images/p/fw/45/PAVF-WA1_V1.jpg",
      "new": "false",
      "category": "bags"
    },
    {
      "id": "67",
      "designer": "BALENCIAGA",
      "title": "Monogram Long Coin Card Holder",
      "price": 57119,
      "image": "https://is4.fwrdassets.com/images/p/fw/45/BALF-WY1451_V1.jpg",
      "new": "false",
      "category": "accessories"
    },
    {
      "id": "68",
      "designer": "TOM FORD",
      "title": "Blake Sunglasses",
      "price": 57119,
      "image": "https://is4.fwrdassets.com/images/p/fw/45/TFOF-WG26_V1.jpg",
      "new": "false",
      "category": "accessories"
    },
    {
      "id": "69",
      "designer": "THE ROW",
      "title": "Ben Bag",
      "price": 57119,
      "image": "https://is4.fwrdassets.com/images/p/fw/45/TERX-WY583_V1.jpg",
      "new": "false",
      "category": "bags"
    },
    {
      "id": "70",
      "designer": "THE ROW",
      "title": "Ben Bag",
      "price": 57119,
      "image": "https://is4.fwrdassets.com/images/p/fw/45/TERX-WY583_V1.jpg",
      "new": "false",
      "category": "bags"
    },
    {
      "id": "71",
      "designer": "AESOP",
      "title": "Eleos Aromatique Hand Balm Tube",
      "price": 57119,
      "image": "https://is4.fwrdassets.com/images/p/fw/45/AESR-WU183_V1.jpg",
      "new": "false",
      "category": "beauty"
    },
    {
      "id": "72",
      "designer": "DAVID KOMA",
      "title": "Crystal Daisy Garter",
      "price": 57119,
      "image": "https://is4.fwrdassets.com/images/p/fw/45/DAVF-WA8_V1.jpg",
      "new": "false",
      "category": "accessories"
    },
    {
      "id": "73",
      "designer": "EMI JAY",
      "title": "Silk Scrunchie",
      "price": 57119,
      "image": "https://is4.fwrdassets.com/images/p/fw/45/EIJF-WA90_V1.jpg",
      "new": "false",
      "category": "accessories"
    },
    {
      "id": "74",
      "designer": "CLYDE",
      "title": "Aries Hat",
      "price": 57119,
      "image": "https://is4.fwrdassets.com/images/p/fw/45/CLYF-WA38_V1.jpg",
      "new": "true",
      "category": "hats"
    },
    {
      "id": "75",
      "designer": "BUSINESS & PLEASURE CO.",
      "title": "Market Umbrella",
      "price": 57119,
      "image": "https://is4.fwrdassets.com/images/p/fw/z/BSUR-WH45_V1.jpg",
      "new": "true",
      "category": "home"
    },
    {
      "id": "76",
      "designer": "WOLFORD",
      "title": "Velvet De Luxe 66 Tights",
      "price": 57119,
      "image": "https://is4.fwrdassets.com/images/p/fw/45/WOLF-WA75_V1.jpg",
      "new": "false",
      "category": "clothing"
    },
    {
      "id": "77",
      "designer": "DEMARSON",
      "title": "Naomi Necklace",
      "price": 57119,
      "image": "https://is4.fwrdassets.com/images/p/fw/z/DRSF-WL33_V1.jpg",
      "new": "false",
      "category": "accessories"
    },
    {
      "id": "78",
      "designer": "SAINT LAURENT",
      "title": "Gaby Key Pouch",
      "price": 57119,
      "image": "https://is4.fwrdassets.com/images/p/fw/45/SLAU-WY2443_V1.jpg",
      "new": "false",
      "category": "accessories"
    },
    {
      "id": "79",
      "designer": "FWRD RENEW",
      "title": "Channel Bucket Hat",
      "price": 57119,
      "image": "https://is4.fwrdassets.com/images/p/fw/45/FNEF-WA127_V1.jpg",
      "new": "false",
      "category": "clothing"
    },
    {
      "id": "80",
      "designer": "STELLA MCCARTNEY",
      "title": "Knit Face Mask",
      "price": 57119,
      "image": "https://is4.fwrdassets.com/images/p/fw/45/SMCC-WA23_V1.jpg",
      "new": "false",
      "category": "accessories"
    },
    {
      "id": "81",
      "designer": "SAINT LAURENT",
      "title": "Grand Scarf",
      "price": 57119,
      "image": "https://is4.fwrdassets.com/images/p/fw/45/SLAU-WA360_V1.jpg",
      "new": "false",
      "category": "accessories"
    },
    {
      "id": "82",
      "designer": "TOM FORD",
      "title": "Moira Sunglasses",
      "price": 57119,
      "image": "https://is4.fwrdassets.com/images/p/fw/45/TFOF-WG30_V1.jpg",
      "new": "false",
      "category": "accessories"
    },
    {
      "id": "83",
      "designer": "BURBERRY",
      "title": "Rectangle Sunglasses",
      "price": 57119,
      "image": "https://is4.fwrdassets.com/images/p/fw/45/BURF-WG4_V1.jpg",
      "new": "false",
      "category": "accessories"
    },
    {
      "id": "84",
      "designer": "SAINT LAURENT",
      "title": "Gaby Chain Phone Holder Bag",
      "price": 57119,
      "image": "https://is4.fwrdassets.com/images/p/fw/45/SLAU-WY2531_V1.jpg",
      "new": "false",
      "category": "bags"
    },
    {
      "id": "85",
      "designer": "GUCCI",
      "title": "Bee Watch",
      "price": 57119,
      "image": "https://is4.fwrdassets.com/images/p/fw/45/GUCC-WL87_V1.jpg",
      "new": "false",
      "category": "watches"
    },
    {
      "id": "86",
      "designer": "AJE",
      "title": "Edith Draped Top",
      "price": 24119,
      "image": "https://is4.fwrdassets.com/images/p/fw/45/GUCC-WL87_V1.jpg",
      "new": "true",
      "category": "clothing"
    },
    {
      "id": "87",
      "designer": "Acne Studios",
      "title": "Bondi Slides",
      "price": 46696,
      "image": "https://is4.fwrdassets.com/images/p/fw/p/ACNE-WZ251_V2.jpg",
      "new": "false",
      "category": "shoes"
    },
    {
      "id": "88",
      "designer": "Coperni",
      "title": "Flower Single Strap Sandals",
      "price": 59204,
      "image": "https://is4.fwrdassets.com/images/p/fw/p/ACNE-WZ251_V2.jpg",
      "new": "true",
      "category": "shoes"
    },
    {
      "id": "89",
      "designer": "KHAITE",
      "title": "Nevada Ankle Stretch 40 Boot",
      "price": 129249,
      "image": "https://is4.fwrdassets.com/images/p/fw/p/KTAH-WZ137_V2.jpg",
      "new": "true",
      "category": "shoes"
    },
    {
      "id": "90",
      "designer": "BALENCIAGA",
      "title": "Biker Bootie",
      "price": 408593,
      "image": "https://is4.fwrdassets.com/images/p/fw/p/BALF-WZ754_V2.jpg",
      "new": "true",
      "category": "shoes"
    },
    {
      "id": "91",
      "designer": "COPERNI",
      "title": "Bridge Boot",
      "price": 65041,
      "image": "https://is4.fwrdassets.com/images/p/fw/p/CRNF-WZ38_V2.jpg",
      "new": "true",
      "category": "shoes"
    },
    {
      "id": "92",
      "designer": "ISABEL MARANT",
      "title": "Witney Boot",
      "price": 120910,
      "image": "https://is4.fwrdassets.com/images/p/fw/p/ISAB-WZ517_V2.jpg",
      "new": "false",
      "category": "shoes"
    },
    {
      "id": "93",
      "designer": "LOEWE",
      "title": "Toy Low Boot",
      "price": 162603,
      "image": "https://is4.fwrdassets.com/images/p/fw/p/LOEW-WZ119_V2.jpg",
      "new": "false",
      "category": "shoes"
    },
    {
      "id": "94",
      "designer": "VALENTINO GARAVANI",
      "title": "V Logo Cut Out Espadrille Slide",
      "price": 60038,
      "image": "https://is4.fwrdassets.com/images/p/fw/p/VENT-WZ854_V4.jpg",
      "new": "true",
      "category": "shoes"
    },
    {
      "id": "95",
      "designer": "VALENTINO GARAVANI",
      "title": "Rockstud Wedge Espadrille",
      "price": 74213,
      "image": "https://is4.fwrdassets.com/images/p/fw/p/VENT-WZ824_V2.jpg",
      "new": "false",
      "category": "shoes"
    },
    {
      "id": "96",
      "designer": "THE ROW",
      "title": "Canal Slip On",
      "price": 74213,
      "image": "https://is4.fwrdassets.com/images/p/fw/p/TERX-WZ325_V2.jpg",
      "new": "false",
      "category": "shoes"
    },
    {
      "id": "97",
      "designer": "BURBERRY",
      "title": "Mesh Ballerina Flat",
      "price": 79217,
      "image": "https://is4.fwrdassets.com/images/p/fw/p/BURF-WZ91_V2.jpg",
      "new": "true",
      "category": "shoes"
    },
    {
      "id": "98",
      "designer": "ISABEL MARANT",
      "title": "Belna Ballet Flat",
      "price": 57953,
      "image": "https://is4.fwrdassets.com/images/p/fw/p/ISAB-WZ538_V2.jpg",
      "new": "false",
      "category": "shoes"
    },
    {
      "id": "99",
      "designer": "FWRD RENEW",
      "title": "Loewe Petal 90 Sandal",
      "price": 86721,
      "image": "https://is4.fwrdassets.com/images/p/fw/p/FNEF-WZ1_V2.jpg",
      "new": "false",
      "category": "shoes"
    },
    {
      "id": "100",
      "designer": "AREA",
      "title": "X Sergio Rossi 95 Pump",
      "price": 99646,
      "image": "https://is4.fwrdassets.com/images/p/fw/p/ARFE-WZ22_V2.jpg",
      "new": "true",
      "category": "shoes"
    },
    {
      "id": "101",
      "designer": "SAINT LAURENT",
      "title": "Le Loafer",
      "price": 90891,
      "image": "https://is4.fwrdassets.com/images/p/fw/p/SLAU-WZ1231_V2.jpg",
      "new": "true",
      "category": "shoes"
    },
    {
      "id": "102",
      "designer": "MIU MIU",
      "title": "x Church's Loafer",
      "price": 122578,
      "image": "https://is4.fwrdassets.com/images/p/fw/p/MIUF-WZ143_V2.jpg",
      "new": "true",
      "category": "shoes"
    },
    {
      "id": "103",
      "designer": "MARNI",
      "title": "Mary Jane High",
      "price": 74630,
      "image": "https://is4.fwrdassets.com/images/p/fw/p/MARN-WZ94_V2.jpg",
      "new": "false",
      "category": "shoes"
    },
    {
      "id": "104",
      "designer": "VALENTINO GARAVANI",
      "title": "Rockstud Slide",
      "price": 79217,
      "image": "https://is4.fwrdassets.com/images/p/fw/p/VENT-WZ841_V2.jpg",
      "new": "true",
      "category": "shoes"
    },
    {
      "id": "105",
      "designer": "PARIS TEXAS",
      "title": "Deia 100 Mule Heel",
      "price": 66292,
      "image": "https://is4.fwrdassets.com/images/p/fw/p/PSTF-WZ258_V2.jpg",
      "new": "false",
      "category": "shoes"
    },
    {
      "id": "106",
      "designer": "RETROFETE",
      "title": "Alessandra Sandal",
      "price": 66542,
      "image": "https://is4.fwrdassets.com/images/p/fw/p/RTFF-WZ14_V2.jpg",
      "new": "true",
      "category": "shoes"
    },
    {
      "id": "107",
      "designer": "BALENCIAGA",
      "title": "Crocs Pool Slide Sandal",
      "price": 60455,
      "image": "https://is4.fwrdassets.com/images/p/fw/p/BALF-WZ759_V2.jpg",
      "new": "true",
      "category": "shoes"
    },
    {
      "id": "108",
      "designer": "GIANVITO ROSSI",
      "title": "Christina Sling Nuit Pump",
      "price": 79217,
      "image": "https://is4.fwrdassets.com/images/p/fw/p/GIAN-WZ750_V2.jpg",
      "new": "true",
      "category": "shoes"
    },
    {
      "id": "109",
      "designer": "BOTTEGA VENETA",
      "title": "Leaf Sandal",
      "price": 120910,
      "image": "https://is4.fwrdassets.com/images/p/fw/p/BOTT-WZ562_V2.jpg",
      "new": "false",
      "category": "shoes"
    },
    {
      "id": "110",
      "designer": "CONVERSE",
      "title": "Run Star Utility Sandal Cx",
      "price": 6670,
      "image": "https://is4.fwrdassets.com/images/p/fw/p/CRSF-WZ129_V2.jpg",
      "new": "false",
      "category": "shoes"
    },
    {
      "id": "111",
      "designer": "DOLCE & GABBANA CASA",
      "title": "All Over Dg Logo Slippers",
      "price": 22931,
      "image": "https://is4.fwrdassets.com/images/p/fw/p/DASF-WZ1_V2.jpg",
      "new": "false",
      "category": "shoes"
    },
    {
      "id": "112",
      "designer": "LUSSO CLOUD",
      "title": "Esto Hairy Suede",
      "price": 12924,
      "image": "https://is4.fwrdassets.com/images/p/fw/p/LCLO-MZ20_V2.jpg",
      "new": "false",
      "category": "shoes"
    },
    {
      "id": "113",
      "designer": "BOTTER",
      "title": "x Reebok Sneakers",
      "price": 30019,
      "image": "https://is4.fwrdassets.com/images/p/fw/p/BOTF-MZ3_V2.jpg",
      "new": "true",
      "category": "shoes"
    },
    {
      "id": "114",
      "designer": "SALOMON",
      "title": "XT-4 OG",
      "price": 18345,
      "image": "https://is4.fwrdassets.com/images/p/fw/p/SMOF-MZ121_V2.jpg",
      "new": "true",
      "category": "shoes"
    },
    {
      "id": "115",
      "designer": "AMINA MUADDI",
      "title": "Lupita Glass PVC Wedge",
      "price": 92142,
      "image": "https://is4.fwrdassets.com/images/p/fw/p/AMUD-WZ376_V2.jpg",
      "new": "true",
      "category": "shoes"
    },
    {
      "id": "116",
      "designer": "AUREUM",
      "title": "Blair Earrings",
      "price": 13175,
      "image": "https://is4.fwrdassets.com/images/p/fw/z/AEUM-WL36_V1.jpg",
      "new": "false",
      "category": "accessories"
    },
    {
      "id": "117",
      "designer": "AUREUM",
      "title": "Genevieve Earrings",
      "price": 20846,
      "image": "https://is4.fwrdassets.com/images/p/fw/z/AEUM-WL41_V2.jpg",
      "new": "false",
      "category": "accessories"
    },
    {
      "id": "118",
      "designer": "AUREUM",
      "title": "Studded Belt",
      "price": 37523,
      "image": "https://is4.fwrdassets.com/images/p/fw/45/AEUM-WA13_V1.jpg",
      "new": "false",
      "category": "accessories"
    },
    {
      "id": "119",
      "designer": "AUREUM",
      "title": "Studded Belt",
      "price": 35723,
      "image": "https://is4.fwrdassets.com/images/p/fw/45/AEUM-WA14_V1.jpg",
      "new": "false",
      "category": "accessories"
    },
    {
      "id": "120",
      "designer": "LPA",
      "title": "Amalia Maxi Skirt",
      "price": 18178,
      "image": "https://is4.fwrdassets.com/images/p/fw/z/LPAR-WQ179_V2.jpg",
      "new": "false",
      "category": "clothing"
    },
    {
      "id": "121",
      "designer": "LPA",
      "title": "Sarita Midi Dress",
      "price": 22347,
      "image": "https://is4.fwrdassets.com/images/p/fw/z/LPAR-WD813_V2.jpg",
      "new": "false",
      "category": "clothing"
    },
    {
      "id": "122",
      "designer": "LPA",
      "title": "Aniella Gown",
      "price": 26516,
      "image": "https://is4.fwrdassets.com/images/p/fw/z/LPAR-WD793_V1.jpg",
      "new": "false",
      "category": "clothing"
    },
    {
      "id": "123",
      "designer": "LPA",
      "title": "Pietra Mini Dress",
      "price": 17344,
      "image": "https://is4.fwrdassets.com/images/p/fw/z/LPAR-WD803_V2.jpg",
      "new": "false",
      "category": "clothing"
    },
    {
      "id": "124",
      "designer": "LPA",
      "title": "Sojinita Cargo Vest Top",
      "price": 14842,
      "image": "https://is4.fwrdassets.com/images/p/fw/z/LPAR-WS670_V1.jpg",
      "new": "false",
      "category": "clothing"
    },
    {
      "id": "125",
      "designer": "MOTHER",
      "title": "The Tripper Ankle",
      "price": 13925,
      "image": "https://is4.fwrdassets.com/images/p/fw/z/MOTH-WJ1477_V1.jpg",
      "new": "false",
      "category": "clothing"
    },
    {
      "id": "126",
      "designer": "MOTHER",
      "title": "The Undercover Cargo Sneak",
      "price": 22347,
      "image": "https://is4.fwrdassets.com/images/p/fw/z/MOTH-WJ1573_V1.jpg",
      "new": "false",
      "category": "clothing"
    },
    {
      "id": "127",
      "designer": "MOTHER",
      "title": "The Jam Shirt",
      "price": 29185,
      "image": "https://is4.fwrdassets.com/images/p/fw/z/MOTH-WS165_V1.jpg",
      "new": "false",
      "category": "clothing"
    },
    {
      "id": "128",
      "designer": "MOTHER",
      "title": "The Up IN Arms",
      "price": 8338,
      "image": "https://is4.fwrdassets.com/images/p/fw/z/MOTH-WS166_V1.jpg",
      "new": "false",
      "category": "clothing"
    },
    {
      "id": "129",
      "designer": "BALENCIAGA",
      "title": "Le Cagole XS Shoulder Bag",
      "price": 170108,
      "image": "https://is4.fwrdassets.com/images/p/fw/45/BALF-WY1439_V1.jpg",
      "new": "false",
      "category": "clothing"
    },
    {
      "id": "130",
      "designer": "BALENCIAGA",
      "title": "BB Soft Flap Small Bag",
      "price": 204296,
      "image": "https://is4.fwrdassets.com/images/p/fw/45/BALF-WY1457_V1.jpg",
      "new": "true",
      "category": "bags"
    },
    {
      "id": "131",
      "designer": "BALENCIAGA",
      "title": "Small Hourglass Top Handle Bag",
      "price": 250159,
      "image": "https://is4.fwrdassets.com/images/p/fw/45/BALF-WY548_V3.jpg",
      "new": "true",
      "category": "bags"
    },
    {
      "id": "132",
      "designer": "BALENCIAGA",
      "title": "Knife Knot Pump",
      "price": 86388,
      "image": "https://is4.fwrdassets.com/images/p/fw/z/BALF-WZ729_V2.jpg",
      "new": "false",
      "category": "shoes"
    },
    {
      "id": "133",
      "designer": "ANASTASIO HOME",
      "title": "Swell Candle Set",
      "price": 16260,
      "image": "https://is4.fwrdassets.com/images/p/fw/45/AOMF-WH42_V3.jpg",
      "new": "true",
      "category": "beauty"
    },
    {
      "id": "134",
      "designer": "ANASTASIO HOME",
      "title": "Calabria Lidded Jar Candle",
      "price": 13758,
      "image": "https://is4.fwrdassets.com/images/p/fw/45/AOMF-WH44_V1.jpg",
      "new": "false",
      "category": "beauty"
    },
    {
      "id": "135",
      "designer": "ANASTASIO HOME",
      "title": "Large Wide Swell Vase",
      "price": 57953,
      "image": "https://is4.fwrdassets.com/images/p/fw/z/AOMF-WH16_V1.jpg",
      "new": "false",
      "category": "beauty"
    },
    {
      "id": "136",
      "designer": "ANASTASIO HOME",
      "title": "The Teo Dish",
      "price": 12507,
      "image": "https://is4.fwrdassets.com/images/p/fw/z/AOMF-WH27_V1.jpg",
      "new": "false",
      "category": "beauty"
    },
    {
      "id": "137",
      "designer": "ANASTASIO HOME",
      "title": "Welcome Pots Set Of 2",
      "price": 31269,
      "image": "https://is4.fwrdassets.com/images/p/fw/z/AOMF-WH15_V2.jpg",
      "new": "false",
      "category": "beauty"
    },
    {
      "id": "138",
      "designer": "ANASTASIO HOME",
      "title": "Welcome Pots Set Of 2",
      "price": 31269,
      "image": "https://is4.fwrdassets.com/images/p/fw/z/AOMF-WH15_V2.jpg",
      "new": "false",
      "category": "beauty"
    },
    {
      "id": "139",
      "designer": "F. MILLER",
      "title": "Tinted Balm Kit",
      "price": 5169,
      "image": "https://is4.fwrdassets.com/images/p/fw/45/FMIF-WU5_V1.jpg",
      "new": "true",
      "category": "beauty"
    },
    {
      "id": "140",
      "designer": "F. MILLER",
      "title": "Necessity Kit",
      "price": 10673,
      "image": "https://is4.fwrdassets.com/images/p/fw/45/FMIF-UU7_V1.jpg",
      "new": "false",
      "category": "beauty"
    },
    {
      "id": "141",
      "designer": "F. MILLER",
      "title": "Toning Mist",
      "price": 4169,
      "image": "https://is4.fwrdassets.com/images/p/fw/45/FMIF-UU9_V1.jpg",
      "new": "false",
      "category": "beauty"
    },
    {
      "id": "142",
      "designer": "VALENTINO GARAVANI",
      "title": "V Logo Signature Jewelry Box",
      "price": 137587,
      "image": "https://is4.fwrdassets.com/images/p/fw/45/VENT-WY1109_V2.jpg",
      "new": "false",
      "category": "beauty"
    },
    {
      "id": "143",
      "designer": "VALENTINO GARAVANI",
      "title": "V-Romask Sunglasses",
      "price": 69210,
      "image": "https://is4.fwrdassets.com/images/p/fw/45/VENT-WG3_V1.jpg",
      "new": "false",
      "category": "accessories"
    },
    {
      "id": "144",
      "designer": "VALENTINO GARAVANI",
      "title": "Pineapple Earrings",
      "price": 107568,
      "image": "https://is4.fwrdassets.com/images/p/fw/z/VENT-WL188_V1.jpg",
      "new": "false",
      "category": "accessories"
    },
    {
      "id": "145",
      "designer": "NICHOLAS",
      "title": "Sage Lace Trim Slip Dress",
      "price": 29602,
      "image": "https://is4.fwrdassets.com/images/p/fw/z/NHOL-WD462_V1.jpg",
      "new": "false",
      "category": "dress"
    },
    {
      "id": "146",
      "designer": "NICHOLAS",
      "title": "Kylie Lace Cutout Gown",
      "price": 34772,
      "image": "https://is4.fwrdassets.com/images/p/fw/z/NHOL-WD461_V1.jpg",
      "new": "false",
      "category": "dress"
    },
    {
      "id": "147",
      "designer": "NICHOLAS",
      "title": "Karis Top",
      "price": 27100,
      "image": "https://is4.fwrdassets.com/images/p/fw/z/NHOL-WS229_V1.jpg",
      "new": "false",
      "category": "dress"
    },
    {
      "id": "148",
      "designer": "NICHOLAS",
      "title": "Drenica Drop Waist Corset Midi Dress",
      "price": 41276,
      "image": "https://is4.fwrdassets.com/images/p/fw/z/NHOL-WD480_V1.jpg",
      "new": "false",
      "category": "dress"
    },
    {
      "id": "149",
      "designer": "NICHOLAS",
      "title": "Ariah Cowl Draped Midi Dress",
      "price": 49614,
      "image": "https://is4.fwrdassets.com/images/p/fw/z/NHOL-WD476_V1.jpg",
      "new": "false",
      "category": "dress"
    },
    {
      "id": "150",
      "designer": "NICHOLAS",
      "title": "Alfina Double Cowl Gown",
      "price": 49614,
      "image": "https://is4.fwrdassets.com/images/p/fw/z/NHOL-WD471_V2.jpg",
      "new": "false",
      "category": "dress"
    },
    {
      "id": "151",
      "designer": "EMI JAY",
      "title": "Big Effing Clip",
      "price": 2835,
      "image": "https://is4.fwrdassets.com/images/p/fw/45/EIJF-WA78_V1.jpg",
      "new": "false",
      "category": "accessories"
    },
    {
      "id": "152",
      "designer": "EMI JAY",
      "title": "Camellia Scrunchie",
      "price": 1334,
      "image": "https://is4.fwrdassets.com/images/p/fw/45/EIJF-WA50_V2.jpg",
      "new": "false",
      "category": "accessories"
    },
    {
      "id": "153",
      "designer": "EMI JAY",
      "title": "For FWRD Crystal Papillon Clip",
      "price": 16677,
      "image": "https://is4.fwrdassets.com/images/p/fw/45/EIJF-WA20_V1.jpg",
      "new": "false",
      "category": "accessories"
    },
    {
      "id": "154",
      "designer": "EMI JAY",
      "title": "For Fwrd Crystal Big Effing Clip",
      "price": 41693,
      "image": "https://is4.fwrdassets.com/images/p/fw/45/EIJF-WA65_V1.jpg",
      "new": "false",
      "category": "accessories"
    },
    {
      "id": "155",
      "designer": "EMI JAY",
      "title": "Pouch",
      "price": 2668,
      "image": "https://is4.fwrdassets.com/images/p/fw/45/EIJF-WA85_V1.jpg",
      "new": "true",
      "category": "accessories"
    },
    {
      "id": "156",
      "designer": "BOTTEGA VENETA",
      "title": "Small Classic Intrecciato Tote Newspaper Bag",
      "price": 366900,
      "image": "https://is4.fwrdassets.com/images/p/fw/45/BOTT-MY223_V1.jpg",
      "new": "true",
      "category": "bags"
    }
  ],
  "designers": [
    {
      "id": "1",
      "name": "A'MMONDE ATELIER"
    },
    {
      "id": "2",
      "name": "A.EMERY"
    },
    {
      "id": "3",
      "name": "A.L.C."
    },
    {
      "id": "4",
      "name": "ACNE STUDIOS"
    },
    {
      "id": "5",
      "name": "ALANUI"
    },
    {
      "id": "6",
      "name": "ALBERTA FERRETTI"
    },
    {
      "id": "7",
      "name": "ALESSANDRA RICH"
    },
    {
      "id": "8",
      "name": "ALEX PERRY"
    },
    {
      "id": "9",
      "name": "ANASTASIO HOME"
    },
    {
      "id": "10",
      "name": "ANDREADAMO"
    },
    {
      "id": "11",
      "name": "BAINA"
    },
    {
      "id": "12",
      "name": "BALENCIAGA"
    },
    {
      "id": "13",
      "name": "BALLY"
    },
    {
      "id": "14",
      "name": "BIANCA"
    },
    {
      "id": "15",
      "name": "BHANDON"
    },
    {
      "id": "16",
      "name": "BIBA DE SOUSA"
    },
    {
      "id": "17",
      "name": "BOTTER"
    },
    {
      "id": "18",
      "name": "BIRKENSTOCK"
    },
    {
      "id": "19",
      "name": "BOYY"
    },
    {
      "id": "20",
      "name": "BRANDON MAXWELL"
    },
    {
      "id": "21",
      "name": "CALLE DEL MAR"
    },
    {
      "id": "22",
      "name": "CAMP HIGH"
    },
    {
      "id": "23",
      "name": "CANADA GOOSE"
    },
    {
      "id": "24",
      "name": "CHRISTOPHE ROBIN"
    },
    {
      "id": "25",
      "name": "CHRISTOPHER ESBER"
    },
    {
      "id": "26",
      "name": "CHRISTOPHER JOHN ROGERS"
    },
    {
      "id": "27",
      "name": "CONVERSE"
    },
    {
      "id": "28",
      "name": "COPERNI"
    },
    {
      "id": "29",
      "name": "CORDOVA"
    },
    {
      "id": "30",
      "name": "CLYDE"
    },
    {
      "id": "31",
      "name": "DRIES VAN NOTEN"
    },
    {
      "id": "32",
      "name": "DR. BARBARA STURM"
    },
    {
      "id": "33",
      "name": "DIOTIMA"
    },
    {
      "id": "34",
      "name": "DION LEE"
    },
    {
      "id": "35",
      "name": "DINOSAUR DESIGNS"
    },
    {
      "id": "36",
      "name": "DIESEL"
    },
    {
      "id": "37",
      "name": "DAVIE OCHO CANDLE CO."
    },
    {
      "id": "38",
      "name": "DAVID KOMA"
    },
    {
      "id": "39",
      "name": "DARKPARK"
    },
    {
      "id": "40",
      "name": "DANIELE CARLOTTA"
    },
    {
      "id": "41",
      "name": "ETRO"
    },
    {
      "id": "42",
      "name": "ETERNE"
    },
    {
      "id": "43",
      "name": "ESCVDO"
    },
    {
      "id": "44",
      "name": "ERL"
    },
    {
      "id": "45",
      "name": "ERES"
    },
    {
      "id": "46",
      "name": "ENZA COSTA"
    },
    {
      "id": "47",
      "name": "ELIOU"
    },
    {
      "id": "48",
      "name": "EERA"
    },
    {
      "id": "49",
      "name": "EDWARD COLLINSON"
    },
    {
      "id": "50",
      "name": "EB DENIM"
    },
    {
      "id": "51",
      "name": "FWRD"
    },
    {
      "id": "52",
      "name": "FREDERIC MALLE"
    },
    {
      "id": "53",
      "name": "FOREO"
    },
    {
      "id": "54",
      "name": "FLEUR DU MAL"
    },
    {
      "id": "55",
      "name": "FLATLIST"
    },
    {
      "id": "56",
      "name": "FLAMINGO ESTATE"
    },
    {
      "id": "57",
      "name": "FE NOEL"
    },
    {
      "id": "58",
      "name": "FANNIE SCHIAVONI"
    },
    {
      "id": "59",
      "name": "FALKE"
    },
    {
      "id": "60",
      "name": "F. MILLER"
    },
    {
      "id": "61",
      "name": "GRLFRND"
    },
    {
      "id": "62",
      "name": "GRACE LING"
    },
    {
      "id": "63",
      "name": "GLOBE-TROTTER"
    },
    {
      "id": "64",
      "name": "GLADYS TAMEZ MILLINERY"
    },
    {
      "id": "65",
      "name": "GIVENCHY"
    },
    {
      "id": "66",
      "name": "GIRLFRIEND COLLECTIVE"
    },
    {
      "id": "67",
      "name": "GARRETT LEIGHT"
    },
    {
      "id": "68",
      "name": "GANNI"
    },
    {
      "id": "69",
      "name": "GALVAN"
    },
    {
      "id": "70",
      "name": "GABRIELA HEARST"
    },
    {
      "id": "71",
      "name": "HOLDEN"
    },
    {
      "id": "72",
      "name": "HOKA"
    },
    {
      "id": "73",
      "name": "HELSA"
    },
    {
      "id": "74",
      "name": "HELMUT LANG"
    },
    {
      "id": "75",
      "name": "HELLE MARDAHL"
    },
    {
      "id": "76",
      "name": "HEIRLOME"
    },
    {
      "id": "77",
      "name": "HARAGO"
    },
    {
      "id": "78",
      "name": "HANNAH POLSKIN"
    },
    {
      "id": "79",
      "name": "HAIKURE"
    },
    {
      "id": "80",
      "name": "HAIGHT"
    },
    {
      "id": "81",
      "name": "IOKA"
    },
    {
      "id": "82",
      "name": "ISABEL MARANT ETOILE"
    },
    {
      "id": "83",
      "name": "ISABEL MARANT"
    },
    {
      "id": "84",
      "name": "IRO"
    },
    {
      "id": "85",
      "name": "INTERIOR"
    },
    {
      "id": "86",
      "name": "ILIO SMERALDO"
    },
    {
      "id": "87",
      "name": "ILIA"
    },
    {
      "id": "88",
      "name": "ILENE JOY"
    },
    {
      "id": "89",
      "name": "ILA"
    },
    {
      "id": "90",
      "name": "IINDACO"
    },
    {
      "id": "91",
      "name": "JOHN ELLIOTT"
    },
    {
      "id": "92",
      "name": "JOHANNA ORTIZ"
    },
    {
      "id": "93",
      "name": "JIMMY CHOO"
    },
    {
      "id": "94",
      "name": "JIL SANDER"
    },
    {
      "id": "95",
      "name": "JENNIFER FISHER"
    },
    {
      "id": "96",
      "name": "JENNIFER BEHR"
    },
    {
      "id": "97",
      "name": "JADE SWIM"
    },
    {
      "id": "98",
      "name": "JADE CROPPER"
    },
    {
      "id": "99",
      "name": "JACQUEMUS"
    },
    {
      "id": "100",
      "name": "J. LOGAN HOME"
    },
    {
      "id": "101",
      "name": "KHAITE"
    },
    {
      "id": "102",
      "name": "KIDSUPER"
    },
    {
      "id": "103",
      "name": "KIKI DE MONTPARNASSE"
    },
    {
      "id": "104",
      "name": "KNC BEAUTY"
    },
    {
      "id": "105",
      "name": "KNWLS"
    },
    {
      "id": "106",
      "name": "KORAL"
    },
    {
      "id": "107",
      "name": "L'ACADEMIE"
    },
    {
      "id": "108",
      "name": "L'AGENCE"
    },
    {
      "id": "109",
      "name": "LA BOUCHE ROUGE"
    },
    {
      "id": "110",
      "name": "LA PERLA"
    },
    {
      "id": "111",
      "name": "LEDA MADERA"
    },
    {
      "id": "112",
      "name": "LELE SADOUGHI"
    },
    {
      "id": "113",
      "name": "LEMAIRE"
    },
    {
      "id": "114",
      "name": "LEONOR GREYL PARIS"
    },
    {
      "id": "115",
      "name": "LOLA HATS"
    },
    {
      "id": "116",
      "name": "LOREN STEWART"
    },
    {
      "id": "117",
      "name": "MACH & MACH"
    },
    {
      "id": "118",
      "name": "MADEWORN"
    },
    {
      "id": "119",
      "name": "MAGDA BUTRYM"
    },
    {
      "id": "120",
      "name": "MAISIE WILEN"
    },
    {
      "id": "121",
      "name": "MASON PEARSON"
    },
    {
      "id": "122",
      "name": "MATTEAU"
    },
    {
      "id": "123",
      "name": "MATTHEW BRUCH"
    },
    {
      "id": "124",
      "name": "MAX ID NY"
    },
    {
      "id": "125",
      "name": "MIU MIU"
    },
    {
      "id": "126",
      "name": "MONCLER"
    },
    {
      "id": "127",
      "name": "NANNETTE DE GASPE"
    },
    {
      "id": "128",
      "name": "NANUSHKA"
    },
    {
      "id": "129",
      "name": "NATALIE MARTIN"
    },
    {
      "id": "130",
      "name": "NATUREOFTHINGS"
    },
    {
      "id": "131",
      "name": "NONFICTION"
    },
    {
      "id": "132",
      "name": "NORMA KAMALI"
    },
    {
      "id": "133",
      "name": "NOUR HAMMOUR"
    },
    {
      "id": "134",
      "name": "NUE STUDIO"
    },
    {
      "id": "135",
      "name": "NERVI"
    },
    {
      "id": "136",
      "name": "NICHOLAS"
    },
    {
      "id": "137",
      "name": "OFF-WHITE"
    },
    {
      "id": "138",
      "name": "OLAPLEX"
    },
    {
      "id": "139",
      "name": "OLIVE ATELIERS"
    },
    {
      "id": "140",
      "name": "OLIVER PEOPLES"
    },
    {
      "id": "141",
      "name": "OLIVIA VON HALLE"
    },
    {
      "id": "142",
      "name": "ON"
    },
    {
      "id": "143",
      "name": "ONE OF THESE DAYS"
    },
    {
      "id": "144",
      "name": "ORMAIE"
    },
    {
      "id": "145",
      "name": "OSCAR DE LA RENTA"
    },
    {
      "id": "146",
      "name": "OSEREE"
    },
    {
      "id": "147",
      "name": "PRE-OWNED"
    },
    {
      "id": "148",
      "name": "PALM"
    },
    {
      "id": "149",
      "name": "PALM ANGELS"
    },
    {
      "id": "150",
      "name": "PALMES"
    },
    {
      "id": "151",
      "name": "PAT MCGRATH LABS"
    },
    {
      "id": "152",
      "name": "PATBO"
    },
    {
      "id": "153",
      "name": "PERFECT MOMENT"
    },
    {
      "id": "154",
      "name": "PETER DO"
    },
    {
      "id": "155",
      "name": "POLO RALPH LAUREN"
    },
    {
      "id": "156",
      "name": "POSSE"
    },
    {
      "id": "157",
      "name": "R13"
    },
    {
      "id": "158",
      "name": "RABANNE"
    },
    {
      "id": "159",
      "name": "RACHEL GILBERT"
    },
    {
      "id": "160",
      "name": "RAF SIMONS"
    },
    {
      "id": "161",
      "name": "RENE CAOVILLA"
    },
    {
      "id": "162",
      "name": "RETROFETE"
    },
    {
      "id": "163",
      "name": "RETROUVE"
    },
    {
      "id": "164",
      "name": "RVE RICHE"
    },
    {
      "id": "165",
      "name": "ROEN"
    },
    {
      "id": "166",
      "name": "ROHE"
    },
    {
      "id": "167",
      "name": "SABLYN"
    },
    {
      "id": "168",
      "name": "SAINT LAURENT"
    },
    {
      "id": "169",
      "name": "SAKS POTTS"
    },
    {
      "id": "170",
      "name": "SALOMON"
    },
    {
      "id": "171",
      "name": "SID NEIGUM"
    },
    {
      "id": "172",
      "name": "SIEDRES"
    },
    {
      "id": "173",
      "name": "SIENA JEWELRY"
    },
    {
      "id": "174",
      "name": "SILVIA TCHERASSI"
    },
    {
      "id": "175",
      "name": "SPINELLI KILCOLLIN"
    },
    {
      "id": "176",
      "name": "SPORTY & RICH"
    },
    {
      "id": "177",
      "name": "TEKLA"
    },
    {
      "id": "178",
      "name": "THE ANDAMANE"
    },
    {
      "id": "179",
      "name": "THE ATTICO"
    },
    {
      "id": "180",
      "name": "THE ELDER STATESMAN"
    },
    {
      "id": "181",
      "name": "THE NORTH FACE"
    },
    {
      "id": "182",
      "name": "THE NUE CO."
    },
    {
      "id": "183",
      "name": "THE RANGE"
    },
    {
      "id": "184",
      "name": "THE ROW"
    },
    {
      "id": "185",
      "name": "TINA FREY DESIGNS"
    },
    {
      "id": "186",
      "name": "TOM FORD"
    },
    {
      "id": "187",
      "name": "U BEAUTY"
    },
    {
      "id": "188",
      "name": "ULLA JOHNSON"
    },
    {
      "id": "189",
      "name": "UNIFROM"
    },
    {
      "id": "187",
      "name": "VALENTINO"
    },
    {
      "id": "188",
      "name": "VALENTINO GARAVANI"
    },
    {
      "id": "189",
      "name": "VANS"
    },
    {
      "id": "190",
      "name": "VANS VAULT"
    },
    {
      "id": "191",
      "name": "VARLEY"
    },
    {
      "id": "192",
      "name": "VEJA"
    },
    {
      "id": "193",
      "name": "VERONICA BEARD"
    },
    {
      "id": "194",
      "name": "VERSACE"
    },
    {
      "id": "195",
      "name": "VICTORIA BECKHAM"
    },
    {
      "id": "196",
      "name": "VINTNER'S DAUGHTER"
    },
    {
      "id": "197",
      "name": "VISION OF SELF"
    },
    {
      "id": "198",
      "name": "WAO"
    },
    {
      "id": "199",
      "name": "WARDROBE.NYC"
    },
    {
      "id": "200",
      "name": "WEEKEND STORIES"
    },
    {
      "id": "201",
      "name": "WELLBEL"
    },
    {
      "id": "202",
      "name": "WIEDERHOEFT"
    },
    {
      "id": "203",
      "name": "WOLFORD"
    },
    {
      "id": "204",
      "name": "WONDER VALLEY"
    },
    {
      "id": "205",
      "name": "YEAR OF OURS"
    },
    {
      "id": "206",
      "name": "Y/PROJECT"
    },
    {
      "id": "207",
      "name": "YVES SALOMON"
    },
    {
      "id": "208",
      "name": "ZANAT"
    },
    {
      "id": "209",
      "name": "ZANKOV"
    },
    {
      "id": "210",
      "name": "ZEYNEP ARCAY"
    },
    {
      "id": "211",
      "name": "ZIIP"
    },
    {
      "id": "212",
      "name": "ZIMMERMANN"
    }
  ]
}